dowhy/__init__.py
dowhy/api/__init__.py
dowhy/api/causal_data_frame.py
dowhy/causal_estimator.py
dowhy/causal_estimators/__init__.py
dowhy/causal_estimators/causalml.py
dowhy/causal_estimators/distance_matching_estimator.py
dowhy/causal_estimators/econml.py
dowhy/causal_estimators/generalized_linear_model_estimator.py
dowhy/causal_estimators/instrumental_variable_estimator.py
dowhy/causal_estimators/linear_regression_estimator.py
dowhy/causal_estimators/propensity_score_estimator.py
dowhy/causal_estimators/propensity_score_matching_estimator.py
dowhy/causal_estimators/propensity_score_stratification_estimator.py
dowhy/causal_estimators/propensity_score_weighting_estimator.py
dowhy/causal_estimators/regression_discontinuity_estimator.py
dowhy/causal_estimators/regression_estimator.py
dowhy/causal_estimators/two_stage_regression_estimator.py
dowhy/causal_graph.py
dowhy/causal_identifier/__init__.py
dowhy/causal_identifier/adjustment_set.py
dowhy/causal_identifier/auto_identifier.py
dowhy/causal_identifier/backdoor.py
dowhy/causal_identifier/efficient_backdoor.py
dowhy/causal_identifier/id_identifier.py
dowhy/causal_identifier/identified_estimand.py
dowhy/causal_identifier/identify_effect.py
dowhy/causal_model.py
dowhy/causal_prediction/__init__.py
dowhy/causal_prediction/algorithms/__init__.py
dowhy/causal_prediction/algorithms/base_algorithm.py
dowhy/causal_prediction/algorithms/cacm.py
dowhy/causal_prediction/algorithms/erm.py
dowhy/causal_prediction/algorithms/regularization.py
dowhy/causal_prediction/algorithms/utils.py
dowhy/causal_prediction/dataloaders/__init__.py
dowhy/causal_prediction/dataloaders/fast_data_loader.py
dowhy/causal_prediction/dataloaders/get_data_loader.py
dowhy/causal_prediction/dataloaders/misc.py
dowhy/causal_prediction/datasets/__init__.py
dowhy/causal_prediction/datasets/base_dataset.py
dowhy/causal_prediction/datasets/mnist.py
dowhy/causal_prediction/models/__init__.py
dowhy/causal_prediction/models/networks.py
dowhy/causal_refuter.py
dowhy-0.13.dist-info/LICENSE
dowhy-0.13.dist-info/METADATA
dowhy-0.13.dist-info/WHEEL
dowhy-0.13.dist-info/RECORD
