Metadata-Version: 2.3
Name: dowhy
Version: 0.13
Summary: DoWhy is a Python library for causal inference that supports explicit modeling and testing of causal assumptions
License: MIT
Keywords: causality,machine-learning,causal-inference,statistics,graphical-model
Author: PyWhy Community
Author-email: amshar@microsoft.com
Requires-Python: >=3.8,<3.13
Classifier: Development Status :: 4 - Beta
Classifier: License :: OSI Approved :: MIT License
Classifier: Programming Language :: Python :: 3
Classifier: Programming Language :: Python :: 3.8
Classifier: Programming Language :: Python :: 3.9
Classifier: Programming Language :: Python :: 3.10
Classifier: Programming Language :: Python :: 3.11
Classifier: Programming Language :: Python :: 3.12
Provides-Extra: econml
Provides-Extra: plotting
Provides-Extra: pydot
Provides-Extra: pygraphviz
Requires-Dist: causal-learn (>=0.1.3.0)
Requires-Dist: cvxpy (<1.5)
Requires-Dist: cython (>=3.0)
Requires-Dist: econml (>=0.15.1) ; extra == "econml"
Requires-Dist: joblib (>=1.1.0)
Requires-Dist: matplotlib (>=3.5.3) ; extra == "plotting"
Requires-Dist: networkx (>=2.8.5) ; python_version < "3.10"
Requires-Dist: networkx (>=3.3) ; python_version >= "3.10"
Requires-Dist: numba (<0.59) ; python_version < "3.9"
Requires-Dist: numba (>=0.59) ; python_version >= "3.9"
Requires-Dist: numpy (<2.0) ; python_version < "3.9"
Requires-Dist: numpy (>1.0) ; python_version >= "3.9"
Requires-Dist: pandas (<2.0) ; python_version < "3.9"
Requires-Dist: pandas (>1.0) ; python_version >= "3.9"
Requires-Dist: pydot (>=1.4.2,<2.0.0) ; extra == "pydot"
Requires-Dist: pygraphviz (>=1.9) ; extra == "pygraphviz"
Requires-Dist: scikit-learn (>1.0)
Requires-Dist: scipy (<=1.15.3) ; python_version >= "3.9" and python_version < "3.13"
Requires-Dist: scipy (>=1.7,<1.14) ; python_version < "3.9"
Requires-Dist: statsmodels (>=0.14)
Requires-Dist: sympy (>=1.10.1)
Requires-Dist: tqdm (>=4.64.0)
Project-URL: Documentation, https://py-why.github.io/dowhy
Project-URL: Repository, https://github.com/py-why/dowhy
